danteai/__init__.py
danteai/create_or_train.py
danteai/get_generated_article.py
danteai/minions.py
danteai/train.py
danteai-1.1.1.dist-info/LICENSE
danteai-1.1.1.dist-info/METADATA
danteai-1.1.1.dist-info/WHEEL
danteai-1.1.1.dist-info/top_level.txt
danteai-1.1.1.dist-info/RECORD
