Metadata-Version: 2.1
Name: danteai
Version: 1.1.1
License-File: LICENSE
Requires-Dist: python-dotenv
Requires-Dist: transformers
Requires-Dist: torch
Requires-Dist: tensorflow
Requires-Dist: datasets
